AUTHORS.rst
CHANGELOG.md
LICENSE
MANIFEST.in
README.md
setup.cfg
setup.py
elvis/__init__.py
elvis/api.py
elvis/enums.py
elvis/models.py
elvis/utils.py
lvis_test_config/__init__.py
lvis_test_config/base.py
python_lvis.egg-info/PKG-INFO
python_lvis.egg-info/SOURCES.txt
python_lvis.egg-info/dependency_links.txt
python_lvis.egg-info/requires.txt
python_lvis.egg-info/top_level.txt