Metadata-Version: 2.1
Name: python-lvis
Version: 1.1.0
Summary: Easy to use redis queue
Home-page: https://thorgate.eu
Author: Thorgate
Author-email: info@thorgate.eu
License: UNKNOWN
Platform: UNKNOWN
Classifier: Development Status :: 4 - Beta
Classifier: Environment :: Web Environment
Classifier: Intended Audience :: Developers
Classifier: License :: OSI Approved :: BSD License
Classifier: Operating System :: OS Independent
Classifier: Programming Language :: Python
Classifier: Programming Language :: Python :: 2
Requires-Python: >=2.7
License-File: LICENSE
License-File: AUTHORS.rst
